LICENSE
cvetrends/__init__.py
cvetrends/__main__.py
cvetrends/lib/message_payload.json
cvetrends/lib/notify.py
cvetrends-0.0.1.dist-info/entry_points.txt
cvetrends-0.0.1.dist-info/LICENSE
cvetrends-0.0.1.dist-info/WHEEL
cvetrends-0.0.1.dist-info/METADATA
cvetrends-0.0.1.dist-info/RECORD
