Metadata-Version: 2.1
Name: cvetrends
Version: 0.0.1
Summary: cvet is a Python utility for pulling actionable vulnerabilities from cvetrends.com
Home-page: https://github.com/puzzlepeaches/cvetrends
License: BSD 3-Clause License
Author: Nicholas
Author-email: nanastasi@sprocketsecurity.com
Requires-Python: >=3.8,<4.0
Classifier: Environment :: Console
Classifier: License :: Other/Proprietary License
Classifier: Programming Language :: Python :: 3
Classifier: Programming Language :: Python :: 3.10
Classifier: Programming Language :: Python :: 3.8
Classifier: Programming Language :: Python :: 3.9
Classifier: Topic :: Security
Requires-Dist: click
Requires-Dist: click-config-file
Requires-Dist: notifiers (>=1.3.3,<2.0.0)
Requires-Dist: python-box (>=6.0.2,<7.0.0)
Requires-Dist: requests (>=2.27.1,<3.0.0)
Requires-Dist: rich (>=12.4.1,<13.0.0)
Requires-Dist: rich-click (>=1.5.2,<2.0.0)
Project-URL: Repository, https://github.com/puzzlepeaches/cvetrends
